phylactery/__init__.py
phylactery/bitset.py
phylactery/fuzzydict.py
phylactery/triedict.py
phylactery/unionfind.py
phylactery/vptree.py
phylactery-0.2.3.dist-info/LICENSE.txt
phylactery-0.2.3.dist-info/METADATA
phylactery-0.2.3.dist-info/WHEEL
phylactery-0.2.3.dist-info/top_level.txt
phylactery-0.2.3.dist-info/zip-safe
phylactery-0.2.3.dist-info/RECORD
