Metadata-Version: 2.1
Name: phylactery
Version: 0.2.3
Summary: Curated collection of data structures for Python.
Home-page: http://github.com/Yomguithereal/phylactery
Author: Guillaume Plique
Author-email: kropotkinepiotr@gmail.com
License: MIT
Keywords: url
Platform: UNKNOWN
